mannigrad/__init__.py
mannigrad/engine.py
mannigrad/nn.py
mannigrad/utils.py
mannigrad-0.1.3.dist-info/WHEEL
mannigrad-0.1.3.dist-info/entry_points.txt
mannigrad-0.1.3.dist-info/METADATA
mannigrad-0.1.3.dist-info/RECORD
