Metadata-Version: 2.3
Name: mannigrad
Version: 0.1.3
Summary: A tiny autograd engine and neural network library.
Author: vainavinair
Author-email: vainavinair <vainavinair2009558@gmail.com>
Requires-Python: >=3.12.4
